plantpredict/__init__.py
plantpredict/api.py
plantpredict/ashrae.py
plantpredict/enumerations.py
plantpredict/error_handlers.py
plantpredict/geo.py
plantpredict/helpers.py
plantpredict/inverter.py
plantpredict/module.py
plantpredict/plant_predict_entity.py
plantpredict/powerplant.py
plantpredict/prediction.py
plantpredict/project.py
plantpredict/utilities.py
plantpredict/weather.py
plantpredict-1.0.22.dist-info/LICENSE
plantpredict-1.0.22.dist-info/METADATA
plantpredict-1.0.22.dist-info/WHEEL
plantpredict-1.0.22.dist-info/top_level.txt
plantpredict-1.0.22.dist-info/RECORD
