Metadata-Version: 2.1
Name: plantpredict
Version: 1.0.22
Summary: Python SDK for PlantPredict (https://ui.plantpredict.terabase.energy).
Home-page: https://github.com/plantpredict/python-sdk
Author: Kurt Rhee & Jese Milam.
Author-email: support@plantpredic.com
License: LICENSE.txt
Requires-Python: >=3.10, <4
License-File: LICENSE
Requires-Dist: requests
Requires-Dist: pandas
Requires-Dist: six
Requires-Dist: mock
Requires-Dist: xlrd
Requires-Dist: openpyxl
